ChangeLog
LICENSE
MANIFEST.in
README.md
README.rst
setup.py
NamedAtomicLock/__init__.py
NamedAtomicLock.egg-info/PKG-INFO
NamedAtomicLock.egg-info/SOURCES.txt
NamedAtomicLock.egg-info/dependency_links.txt
NamedAtomicLock.egg-info/top_level.txt
doc/NamedAtomicLock.html
doc/index.html
tests/runTests.py
tests/NamedAtomicLockTests/test_Expiration1.py
tests/NamedAtomicLockTests/test_Expiration2.py
tests/NamedAtomicLockTests/test_General.py
tests/NamedAtomicLockTests/test_Locking.py