Metadata-Version: 1.1
Name: NamedAtomicLock
Version: 1.1.3
Summary: Python module for an atomic named interprocess lock which is local to the machine.
Home-page: https://github.com/kata198/NamedAtomicLock
Author: Tim Savannah
Author-email: kata198@gmail.com
License: LGPLv3
Keywords: lock,named,atomic,mkdir,posix,acquire,release
Platform: UNKNOWN
Classifier: Development Status :: 5 - Production/Stable
Classifier: Programming Language :: Python
Classifier: License :: OSI Approved :: GNU Lesser General Public License v3 (LGPLv3)
Classifier: Programming Language :: Python :: 2
Classifier: Programming Language :: Python :: 2
Classifier: Programming Language :: Python :: 2.6
Classifier: Programming Language :: Python :: 2.7
Classifier: Programming Language :: Python :: 3
Classifier: Programming Language :: Python :: 3.3
Classifier: Programming Language :: Python :: 3.4
Classifier: Programming Language :: Python :: 3.5
Classifier: Programming Language :: Python :: 3.6
Classifier: Topic :: Software Development :: Libraries :: Python Modules
